pygbm/__init__.py
pygbm/cli.py
pygbm/gbm_simulator.py
pygbm/version.py
ljf441_pygbm-0.0.post53.dist-info/METADATA
ljf441_pygbm-0.0.post53.dist-info/WHEEL
ljf441_pygbm-0.0.post53.dist-info/entry_points.txt
ljf441_pygbm-0.0.post53.dist-info/top_level.txt
ljf441_pygbm-0.0.post53.dist-info/RECORD
